README.md
setup.py
pyramid_https_session_redis/__init__.py
pyramid_https_session_redis.egg-info/PKG-INFO
pyramid_https_session_redis.egg-info/SOURCES.txt
pyramid_https_session_redis.egg-info/dependency_links.txt
pyramid_https_session_redis.egg-info/not-zip-safe
pyramid_https_session_redis.egg-info/requires.txt
pyramid_https_session_redis.egg-info/top_level.txt